cli/__init__.py
cli/main.py
cli/commands/__init__.py
cli/commands/batch.py
cli/commands/cache.py
cli/commands/convert.py
cli/commands/info.py
cli/ui/__init__.py
cli/ui/file_picker.py
cli/ui/progress_bar.py
config/__init__.py
config/conversion_profiles.json
config/logging_config.yaml
config/settings.py
converter/__init__.py
converter/batch_processor.py
converter/conversion_chain.py
converter/engine.py
converter/template_engine.py
converter/base/__init__.py
converter/base/converter_base.py
converter/base/format_detector.py
converter/base/metadata_extractor.py
converter/formats/__init__.py
converter/formats/docx_converter.py
converter/formats/docx_writer.py
converter/formats/format_detector.py
converter/formats/html_converter.py
converter/formats/markdown_converter.py
converter/formats/odt_converter.py
converter/formats/odt_writer.py
converter/formats/pdf_converter.py
converter/formats/pdf_writer.py
converter/formats/txt_converter.py
converter/processors/image_processor.py
converter/processors/ocr_processor.py
converter/processors/style_processor.py
converter/processors/table_processor.py
core/__init__.py
core/cache_manager.py
core/error_handler.py
core/file_handler.py
core/lifecycle.py
core/logger.py
core/progress_tracker.py
core/registry.py
core/task_queue.py
core/transaction.py
core/worker_pool.py
utils/__init__.py
utils/lazy_loader.py
utils/path_manager.py
utils/validation.py
document_converter-1.2.0.dist-info/METADATA
document_converter-1.2.0.dist-info/WHEEL
document_converter-1.2.0.dist-info/entry_points.txt
document_converter-1.2.0.dist-info/top_level.txt
document_converter-1.2.0.dist-info/RECORD
