Metadata-Version: 2.4
Name: document-converter
Version: 1.2.0
Summary: Comprehensive document conversion library with batch processing, caching, and template rendering
Home-page: https://github.com/MikeAMSDev/document-converter
Author: Document Converter Team
Author-email: dev@example.com
Project-URL: Bug Tracker, https://github.com/MikeAMSDev/document-converter/issues
Project-URL: Source Code, https://github.com/MikeAMSDev/document-converter
Project-URL: Changelog, https://github.com/MikeAMSDev/document-converter/blob/main/CHANGELOG.md
Keywords: document,conversion,pdf,docx,html,markdown,batch,processing,caching,template,rendering
Classifier: Development Status :: 5 - Production/Stable
Classifier: Intended Audience :: Developers
Classifier: License :: OSI Approved :: MIT License
Classifier: Operating System :: OS Independent
Classifier: Programming Language :: Python :: 3
Classifier: Programming Language :: Python :: 3.9
Classifier: Programming Language :: Python :: 3.10
Classifier: Programming Language :: Python :: 3.11
Classifier: Programming Language :: Python :: 3.12
Classifier: Topic :: Software Development :: Libraries :: Python Modules
Classifier: Topic :: Text Processing :: General
Classifier: Topic :: Office/Business
Requires-Python: >=3.9
Requires-Dist: pypdf2==3.0.1
Requires-Dist: reportlab==4.0.7
Requires-Dist: python-docx==1.1.0
Requires-Dist: odfpy==1.4.1
Requires-Dist: markdown==3.5.1
Requires-Dist: beautifulsoup4==4.12.2
Requires-Dist: lxml==5.3.2
Requires-Dist: html5lib==1.1
Requires-Dist: Pillow<13,==11.0.0
Requires-Dist: img2pdf==0.5.0
Requires-Dist: pytesseract==0.3.10
Requires-Dist: pdf2image==1.16.3
Requires-Dist: pypdf2==3.0.1
Requires-Dist: reportlab==4.0.7
Requires-Dist: python-docx==1.1.0
Requires-Dist: odfpy==1.4.1
Requires-Dist: markdown==3.5.1
Requires-Dist: beautifulsoup4==4.12.2
Requires-Dist: lxml==5.3.2
Requires-Dist: html5lib==1.1
Requires-Dist: Pillow<13,==11.0.0
Requires-Dist: img2pdf==0.5.0
Requires-Dist: pytesseract==0.3.10
Requires-Dist: pdf2image==1.16.3
Requires-Dist: chardet==5.2.0
Requires-Dist: python-magic==0.4.27
Requires-Dist: tqdm==4.66.1
Requires-Dist: pyyaml==6.0.1
Requires-Dist: python-dotenv==1.0.0
Requires-Dist: colorama==0.4.6
Requires-Dist: click==8.1.7
Requires-Dist: html2text==2024.2.26
Provides-Extra: dev
Requires-Dist: pytest==7.4.3; extra == "dev"
Requires-Dist: pytest-cov==4.1.0; extra == "dev"
Requires-Dist: pytest-mock==3.12.0; extra == "dev"
Requires-Dist: pytest-xdist==3.5.0; extra == "dev"
Requires-Dist: black==23.12.1; extra == "dev"
Requires-Dist: flake8==7.0.0; extra == "dev"
Requires-Dist: isort==5.13.2; extra == "dev"
Requires-Dist: mypy==1.8.0; extra == "dev"
Requires-Dist: pylint==3.0.3; extra == "dev"
Requires-Dist: sphinx==7.2.6; extra == "dev"
Requires-Dist: sphinx-rtd-theme==2.0.0; extra == "dev"
Provides-Extra: docs
Requires-Dist: sphinx>=7.0.0; extra == "docs"
Requires-Dist: sphinx-rtd-theme>=2.0.0; extra == "docs"
Requires-Dist: m2r2>=0.3.0; extra == "docs"
Dynamic: author
Dynamic: author-email
Dynamic: classifier
Dynamic: description
Dynamic: description-content-type
Dynamic: home-page
Dynamic: keywords
Dynamic: project-url
Dynamic: provides-extra
Dynamic: requires-dist
Dynamic: requires-python
Dynamic: summary
